py_bitcoinkernel-0.1.0a3.dist-info/WHEEL
py_bitcoinkernel-0.1.0a3.dist-info/RECORD
py_bitcoinkernel-0.1.0a3.dist-info/METADATA
py_bitcoinkernel-0.1.0a3.dist-info/licenses/LICENSE
pbk/chain.py
pbk/notifications.py
pbk/context.py
pbk/log.py
pbk/block.py
pbk/script.py
pbk/validation.py
pbk/__init__.py
pbk/transaction.py
pbk/util/exc.py
pbk/util/type.py
pbk/util/callbacks.py
pbk/util/__init__.py
pbk/_libs/libbitcoinkernel.so
pbk/capi/base.py
pbk/capi/__init__.py
pbk/capi/bindings.py
