Metadata-Version: 2.2
Name: py-bitcoinkernel
Version: 0.1.0a3
Summary: A Python wrapper for libbitcoinkernel
Author-Email: Stephan Vuylsteke <stickies-v@protonmail.com>
License: MIT
Requires-Python: >=3.10
Provides-Extra: test
Requires-Dist: coverage[toml]; extra == "test"
Requires-Dist: pytest>=7.0; extra == "test"
Requires-Dist: pytest-cov; extra == "test"
